LICENSE
README.md
setup.py
enscale/__init__.py
enscale/callback.py
enscale/environ.py
enscale/epochvisor.py
enscale/feature_column.py
enscale/inputs.py
enscale/loss_fn.py
enscale/preprocessing.py
enscale/train_fn.py
enscale/trainer.py
enscale/version.py
enscale.egg-info/PKG-INFO
enscale.egg-info/SOURCES.txt
enscale.egg-info/dependency_links.txt
enscale.egg-info/requires.txt
enscale.egg-info/top_level.txt
enscale/heterogeneous/__init__.py
enscale/heterogeneous/ps.py
enscale/heterogeneous/strategy.py
enscale/layer/__init__.py
enscale/layer/activation.py
enscale/layer/core.py
enscale/layer/interaction.py
enscale/model/__init__.py
enscale/model/ctr/__init__.py
enscale/model/ctr/base.py
enscale/model/ctr/deepfm.py
enscale/model/ctr/fm.py
enscale/model/ctr/fnn.py
enscale/model/ctr/lr.py
enscale/model/ctr/pnn.py
enscale/model/ctr/wdl.py
enscale/optimizer/__init__.py
enscale/optimizer/ftrl.py
enscale/optimizer/stack.py
enscale/util/__init__.py
enscale/util/benchmark_loader.py
enscale/util/common.py