Metadata-Version: 2.1
Name: enscale
Version: 0.0.3.post4
Summary: Enscale: An instant distributed computing library based on Ray stack
Home-page: https://github.com/ryantd/enscale
Author: Xiaoyu Zhai
Author-email: xiaoyu.zhai@hotmail.com
License: UNKNOWN
Platform: UNKNOWN
Requires-Python: >=3.7.1
License-File: LICENSE
